epd2in13/__init__.py
epd2in13-0.1.2.dist-info/LICENSE
epd2in13-0.1.2.dist-info/METADATA
epd2in13-0.1.2.dist-info/WHEEL
epd2in13-0.1.2.dist-info/top_level.txt
epd2in13-0.1.2.dist-info/RECORD
