Metadata-Version: 2.1
Name: epd2in13
Version: 0.1.2
Summary: 2.13inch e-Paper HAT - Implements for e-paper library
Home-page: https://github.com/t4skforce/edp2in13
Author: Yehui from Waveshare
Author-email: service@waveshare.com
License: GPL
Platform: UNKNOWN
Classifier: Programming Language :: Python
Classifier: Programming Language :: Python :: 3
Requires-Dist: RPi.GPIO
Requires-Dist: epdif
Requires-Dist: Pillow
